{
  "total": 77,
  "difficulty_counts": {
    "Easy": 18,
    "Medium": 46,
    "Hard": 13
  },
  "tag_counts": {
    "Tree": 16,
    "Depth-First Search": 14,
    "Breadth-First Search": 7,
    "Binary Tree": 16,
    "Hash Table": 21,
    "String": 15,
    "Sliding Window": 6,
    "Design": 10,
    "Linked List": 14,
    "Doubly-Linked List": 2,
    "Array": 33,
    "Divide and Conquer": 7,
    "Bucket Sort": 1,
    "Counting": 2,
    "Quickselect": 3,
    "Sorting": 11,
    "Heap (Priority Queue)": 10,
    "Binary Search": 10,
    "Matrix": 3,
    "Recursion": 6,
    "Two Pointers": 13,
    "Stack": 10,
    "Monotonic Stack": 4,
    "Merge Sort": 1,
    "Math": 6,
    "Greedy": 2,
    "Dynamic Programming": 4,
    "Binary Search Tree": 4,
    "Geometry": 1,
    "Union Find": 1,
    "String Matching": 1,
    "Hash Function": 1,
    "Trie": 3,
    "Backtracking": 1,
    "Prefix Sum": 2,
    "Queue": 1,
    "Monotonic Queue": 1,
    "Bit Manipulation": 1,
    "Data Stream": 2
  }
}